fcm_notifier/__init__.py
fcm_notifier/config.py
fcm_notifier/consts.py
fcm_notifier/helpers.py
fcm_notifier/notification.py
fcm_notifier/queue.py
fcm_notifier/results.py
fcm_notifier/sender.py
fcm_notifier/serializers.py
fcm_notifier/settings.py
fcm_notifier/utils.py
fcm_notifier/version.py
fcm_notifier/worker.py
fcm_notifier/cli/__init__.py
fcm_notifier/cli/cli.py
fcm_notifier-0.2.3.dist-info/METADATA
fcm_notifier-0.2.3.dist-info/WHEEL
fcm_notifier-0.2.3.dist-info/entry_points.txt
fcm_notifier-0.2.3.dist-info/top_level.txt
fcm_notifier-0.2.3.dist-info/RECORD
