Metadata-Version: 2.1
Name: fcm-notifier
Version: 0.2.3
Summary: Сервис отправки push-уведомлений через FCM
Author: BARS Group
Author-email: education_dev@bars-open.ru
License: MIT
Classifier: Development Status :: 3 - Alpha
Classifier: Intended Audience :: Developers
Classifier: License :: OSI Approved :: MIT License
Classifier: Natural Language :: Russian
Classifier: Operating System :: POSIX
Classifier: Operating System :: MacOS
Classifier: Operating System :: Unix
Classifier: Programming Language :: Python
Classifier: Programming Language :: Python :: 3
Classifier: Programming Language :: Python :: 3.7
Classifier: Programming Language :: Python :: 3.8
Classifier: Programming Language :: Python :: 3.9
Requires-Python: >=3.7
Requires-Dist: click >=8.1.3
Requires-Dist: redis >=3.5.3
Requires-Dist: firebase-admin ==6.2.0
